{
    "os": "Linux-5.4.0-162-generic-x86_64-with-glibc2.31",
    "python": "3.10.13",
    "heartbeatAt": "2024-02-19T21:30:26.451928",
    "startedAt": "2024-02-19T21:30:25.634522",
    "docker": null,
    "cuda": null,
    "args": [],
    "state": "running",
    "program": "/sailhome/andukuri/research_projects/assistant-gate/experiments/v3/sft/train/train_sft.py",
    "codePathLocal": "train_sft.py",
    "codePath": "experiments/v3/sft/train/train_sft.py",
    "git": {
        "remote": "git@github.com:scandukuri/assistant-gate.git",
        "commit": "f8363af8df3975a6e7aa8d51faed3673a194e927"
    },
    "email": "andukuri@stanford.edu",
    "root": "/sailhome/andukuri/research_projects/assistant-gate",
    "host": "cocoflops2",
    "username": "andukuri",
    "executable": "/scr/andukuri/miniconda3/envs/assistant-gate/bin/python",
    "cpu_count": 64,
    "cpu_count_logical": 128,
    "cpu_freq": {
        "current": 2267.755140624999,
        "min": 1500.0,
        "max": 2800.0
    },
    "cpu_freq_per_core": [
        {
            "current": 1499.915,
            "min": 1500.0,
            "max": 2800.0
        },
        {
            "current": 1496.658,
            "min": 1500.0,
            "max": 2800.0
        },
        {
            "current": 1796.652,
            "min": 1500.0,
            "max": 2800.0
        },
        {
            "current": 1487.759,
            "min": 1500.0,
            "max": 2800.0
        },
        {
            "current": 1742.159,
            "min": 1500.0,
            "max": 2800.0
        },
        {
            "current": 1684.321,
            "min": 1500.0,
            "max": 2800.0
        },
        {
            "current": 1878.324,
            "min": 1500.0,
            "max": 2800.0
        },
        {
            "current": 2216.507,
            "min": 1500.0,
            "max": 2800.0
        },
        {
            "current": 2874.704,
            "min": 1500.0,
            "max": 2800.0
        },
        {
            "current": 3599.032,
            "min": 1500.0,
            "max": 2800.0
        },
        {
            "current": 2537.526,
            "min": 1500.0,
            "max": 2800.0
        },
        {
            "current": 2877.626,
            "min": 1500.0,
            "max": 2800.0
        },
        {
            "current": 1498.061,
            "min": 1500.0,
            "max": 2800.0
        },
        {
            "current": 1496.012,
            "min": 1500.0,
            "max": 2800.0
        },
        {
            "current": 1498.195,
            "min": 1500.0,
            "max": 2800.0
        },
        {
            "current": 1497.284,
            "min": 1500.0,
            "max": 2800.0
        },
        {
            "current": 1496.096,
            "min": 1500.0,
            "max": 2800.0
        },
        {
            "current": 1499.203,
            "min": 1500.0,
            "max": 2800.0
        },
        {
            "current": 1496.678,
            "min": 1500.0,
            "max": 2800.0
        },
        {
            "current": 1497.178,
            "min": 1500.0,
            "max": 2800.0
        },
        {
            "current": 3599.02,
            "min": 1500.0,
            "max": 2800.0
        },
        {
            "current": 2879.251,
            "min": 1500.0,
            "max": 2800.0
        },
        {
            "current": 3596.802,
            "min": 1500.0,
            "max": 2800.0
        },
        {
            "current": 2877.505,
            "min": 1500.0,
            "max": 2800.0
        },
        {
            "current": 2879.096,
            "min": 1500.0,
            "max": 2800.0
        },
        {
            "current": 2879.16,
            "min": 1500.0,
            "max": 2800.0
        },
        {
            "current": 2769.252,
            "min": 1500.0,
            "max": 2800.0
        },
        {
            "current": 3286.745,
            "min": 1500.0,
            "max": 2800.0
        },
        {
            "current": 1495.597,
            "min": 1500.0,
            "max": 2800.0
        },
        {
            "current": 1497.631,
            "min": 1500.0,
            "max": 2800.0
        },
        {
            "current": 1496.354,
            "min": 1500.0,
            "max": 2800.0
        },
        {
            "current": 1494.833,
            "min": 1500.0,
            "max": 2800.0
        },
        {
            "current": 1793.308,
            "min": 1500.0,
            "max": 2800.0
        },
        {
            "current": 1801.032,
            "min": 1500.0,
            "max": 2800.0
        },
        {
            "current": 1498.807,
            "min": 1500.0,
            "max": 2800.0
        },
        {
            "current": 1497.178,
            "min": 1500.0,
            "max": 2800.0
        },
        {
            "current": 2835.223,
            "min": 1500.0,
            "max": 2800.0
        },
        {
            "current": 2834.654,
            "min": 1500.0,
            "max": 2800.0
        },
        {
            "current": 3549.88,
            "min": 1500.0,
            "max": 2800.0
        },
        {
            "current": 2837.843,
            "min": 1500.0,
            "max": 2800.0
        },
        {
            "current": 2837.687,
            "min": 1500.0,
            "max": 2800.0
        },
        {
            "current": 3590.348,
            "min": 1500.0,
            "max": 2800.0
        },
        {
            "current": 2831.573,
            "min": 1500.0,
            "max": 2800.0
        },
        {
            "current": 2836.642,
            "min": 1500.0,
            "max": 2800.0
        },
        {
            "current": 2837.632,
            "min": 1500.0,
            "max": 2800.0
        },
        {
            "current": 2833.939,
            "min": 1500.0,
            "max": 2800.0
        },
        {
            "current": 2836.83,
            "min": 1500.0,
            "max": 2800.0
        },
        {
            "current": 3545.46,
            "min": 1500.0,
            "max": 2800.0
        },
        {
            "current": 2832.964,
            "min": 1500.0,
            "max": 2800.0
        },
        {
            "current": 2833.833,
            "min": 1500.0,
            "max": 2800.0
        },
        {
            "current": 3546.892,
            "min": 1500.0,
            "max": 2800.0
        },
        {
            "current": 2832.288,
            "min": 1500.0,
            "max": 2800.0
        },
        {
            "current": 1495.59,
            "min": 1500.0,
            "max": 2800.0
        },
        {
            "current": 1498.933,
            "min": 1500.0,
            "max": 2800.0
        },
        {
            "current": 1798.3,
            "min": 1500.0,
            "max": 2800.0
        },
        {
            "current": 1499.774,
            "min": 1500.0,
            "max": 2800.0
        },
        {
            "current": 1553.793,
            "min": 1500.0,
            "max": 2800.0
        },
        {
            "current": 1497.191,
            "min": 1500.0,
            "max": 2800.0
        },
        {
            "current": 1566.614,
            "min": 1500.0,
            "max": 2800.0
        },
        {
            "current": 1497.308,
            "min": 1500.0,
            "max": 2800.0
        },
        {
            "current": 1554.493,
            "min": 1500.0,
            "max": 2800.0
        },
        {
            "current": 1497.617,
            "min": 1500.0,
            "max": 2800.0
        },
        {
            "current": 1566.101,
            "min": 1500.0,
            "max": 2800.0
        },
        {
            "current": 1496.278,
            "min": 1500.0,
            "max": 2800.0
        },
        {
            "current": 1498.206,
            "min": 1500.0,
            "max": 2800.0
        },
        {
            "current": 1494.306,
            "min": 1500.0,
            "max": 2800.0
        },
        {
            "current": 1904.814,
            "min": 1500.0,
            "max": 2800.0
        },
        {
            "current": 1497.247,
            "min": 1500.0,
            "max": 2800.0
        },
        {
            "current": 2878.136,
            "min": 1500.0,
            "max": 2800.0
        },
        {
            "current": 3598.825,
            "min": 1500.0,
            "max": 2800.0
        },
        {
            "current": 2891.358,
            "min": 1500.0,
            "max": 2800.0
        },
        {
            "current": 2876.278,
            "min": 1500.0,
            "max": 2800.0
        },
        {
            "current": 2885.545,
            "min": 1500.0,
            "max": 2800.0
        },
        {
            "current": 3611.218,
            "min": 1500.0,
            "max": 2800.0
        },
        {
            "current": 2886.298,
            "min": 1500.0,
            "max": 2800.0
        },
        {
            "current": 2877.483,
            "min": 1500.0,
            "max": 2800.0
        },
        {
            "current": 1495.79,
            "min": 1500.0,
            "max": 2800.0
        },
        {
            "current": 1495.572,
            "min": 1500.0,
            "max": 2800.0
        },
        {
            "current": 1496.83,
            "min": 1500.0,
            "max": 2800.0
        },
        {
            "current": 1496.93,
            "min": 1500.0,
            "max": 2800.0
        },
        {
            "current": 1501.783,
            "min": 1500.0,
            "max": 2800.0
        },
        {
            "current": 1389.239,
            "min": 1500.0,
            "max": 2800.0
        },
        {
            "current": 1410.861,
            "min": 1500.0,
            "max": 2800.0
        },
        {
            "current": 1418.134,
            "min": 1500.0,
            "max": 2800.0
        },
        {
            "current": 2765.424,
            "min": 1500.0,
            "max": 2800.0
        },
        {
            "current": 2957.593,
            "min": 1500.0,
            "max": 2800.0
        },
        {
            "current": 2844.732,
            "min": 1500.0,
            "max": 2800.0
        },
        {
            "current": 2191.926,
            "min": 1500.0,
            "max": 2800.0
        },
        {
            "current": 2243.514,
            "min": 1500.0,
            "max": 2800.0
        },
        {
            "current": 2238.386,
            "min": 1500.0,
            "max": 2800.0
        },
        {
            "current": 1990.842,
            "min": 1500.0,
            "max": 2800.0
        },
        {
            "current": 2610.438,
            "min": 1500.0,
            "max": 2800.0
        },
        {
            "current": 1380.655,
            "min": 1500.0,
            "max": 2800.0
        },
        {
            "current": 1373.638,
            "min": 1500.0,
            "max": 2800.0
        },
        {
            "current": 1382.096,
            "min": 1500.0,
            "max": 2800.0
        },
        {
            "current": 1394.69,
            "min": 1500.0,
            "max": 2800.0
        },
        {
            "current": 2193.169,
            "min": 1500.0,
            "max": 2800.0
        },
        {
            "current": 2190.337,
            "min": 1500.0,
            "max": 2800.0
        },
        {
            "current": 1921.268,
            "min": 1500.0,
            "max": 2800.0
        },
        {
            "current": 1995.281,
            "min": 1500.0,
            "max": 2800.0
        },
        {
            "current": 2006.991,
            "min": 1500.0,
            "max": 2800.0
        },
        {
            "current": 1969.933,
            "min": 1500.0,
            "max": 2800.0
        },
        {
            "current": 2573.18,
            "min": 1500.0,
            "max": 2800.0
        },
        {
            "current": 1886.423,
            "min": 1500.0,
            "max": 2800.0
        },
        {
            "current": 1814.224,
            "min": 1500.0,
            "max": 2800.0
        },
        {
            "current": 2289.796,
            "min": 1500.0,
            "max": 2800.0
        },
        {
            "current": 2271.923,
            "min": 1500.0,
            "max": 2800.0
        },
        {
            "current": 1901.234,
            "min": 1500.0,
            "max": 2800.0
        },
        {
            "current": 1867.025,
            "min": 1500.0,
            "max": 2800.0
        },
        {
            "current": 1880.706,
            "min": 1500.0,
            "max": 2800.0
        },
        {
            "current": 1876.86,
            "min": 1500.0,
            "max": 2800.0
        },
        {
            "current": 2313.672,
            "min": 1500.0,
            "max": 2800.0
        },
        {
            "current": 2243.167,
            "min": 1500.0,
            "max": 2800.0
        },
        {
            "current": 1865.369,
            "min": 1500.0,
            "max": 2800.0
        },
        {
            "current": 2376.543,
            "min": 1500.0,
            "max": 2800.0
        },
        {
            "current": 1926.962,
            "min": 1500.0,
            "max": 2800.0
        },
        {
            "current": 1101.004,
            "min": 1500.0,
            "max": 2800.0
        },
        {
            "current": 1152.183,
            "min": 1500.0,
            "max": 2800.0
        },
        {
            "current": 1248.233,
            "min": 1500.0,
            "max": 2800.0
        },
        {
            "current": 1167.006,
            "min": 1500.0,
            "max": 2800.0
        },
        {
            "current": 1120.175,
            "min": 1500.0,
            "max": 2800.0
        },
        {
            "current": 1498.019,
            "min": 1500.0,
            "max": 2800.0
        },
        {
            "current": 1496.488,
            "min": 1500.0,
            "max": 2800.0
        },
        {
            "current": 1496.793,
            "min": 1500.0,
            "max": 2800.0
        },
        {
            "current": 1497.163,
            "min": 1500.0,
            "max": 2800.0
        },
        {
            "current": 1495.704,
            "min": 1500.0,
            "max": 2800.0
        },
        {
            "current": 1495.881,
            "min": 1500.0,
            "max": 2800.0
        },
        {
            "current": 1496.685,
            "min": 1500.0,
            "max": 2800.0
        }
    ],
    "disk": {
        "/": {
            "total": 437.88097381591797,
            "used": 130.18986129760742
        }
    },
    "gpu": "NVIDIA A100-SXM4-80GB",
    "gpu_count": 2,
    "gpu_devices": [
        {
            "name": "NVIDIA A100-SXM4-80GB",
            "memory_total": 85899345920
        },
        {
            "name": "NVIDIA A100-SXM4-80GB",
            "memory_total": 85899345920
        }
    ],
    "memory": {
        "total": 1007.7270240783691
    }
}
