{
    "os": "Linux-5.4.0-162-generic-x86_64-with-glibc2.31",
    "python": "3.10.13",
    "heartbeatAt": "2024-02-29T04:26:25.057616",
    "startedAt": "2024-02-29T04:26:24.613262",
    "docker": null,
    "cuda": null,
    "args": [
        "model=m0",
        "split=A"
    ],
    "state": "running",
    "program": "/sailhome/andukuri/research_projects/assistant-gate/experiments/star-1-mistral-ablation/sft/train/train_sft.py",
    "codePathLocal": "train_sft.py",
    "codePath": "experiments/star-1-mistral-ablation/sft/train/train_sft.py",
    "git": {
        "remote": "git@github.com:scandukuri/assistant-gate.git",
        "commit": "cceac5f4d8f0e072ee92f3182ad12489efb87567"
    },
    "email": "andukuri@stanford.edu",
    "root": "/sailhome/andukuri/research_projects/assistant-gate",
    "host": "cocoflops2",
    "username": "andukuri",
    "executable": "/scr/andukuri/miniconda3/envs/assistant-gate/bin/python",
    "cpu_count": 64,
    "cpu_count_logical": 128,
    "cpu_freq": {
        "current": 2112.5836406250005,
        "min": 1500.0,
        "max": 2800.0
    },
    "cpu_freq_per_core": [
        {
            "current": 1499.745,
            "min": 1500.0,
            "max": 2800.0
        },
        {
            "current": 1499.173,
            "min": 1500.0,
            "max": 2800.0
        },
        {
            "current": 1796.199,
            "min": 1500.0,
            "max": 2800.0
        },
        {
            "current": 1496.346,
            "min": 1500.0,
            "max": 2800.0
        },
        {
            "current": 1794.352,
            "min": 1500.0,
            "max": 2800.0
        },
        {
            "current": 1797.145,
            "min": 1500.0,
            "max": 2800.0
        },
        {
            "current": 1497.181,
            "min": 1500.0,
            "max": 2800.0
        },
        {
            "current": 1496.9,
            "min": 1500.0,
            "max": 2800.0
        },
        {
            "current": 1498.725,
            "min": 1500.0,
            "max": 2800.0
        },
        {
            "current": 1496.423,
            "min": 1500.0,
            "max": 2800.0
        },
        {
            "current": 1496.919,
            "min": 1500.0,
            "max": 2800.0
        },
        {
            "current": 1495.859,
            "min": 1500.0,
            "max": 2800.0
        },
        {
            "current": 1796.394,
            "min": 1500.0,
            "max": 2800.0
        },
        {
            "current": 1798.303,
            "min": 1500.0,
            "max": 2800.0
        },
        {
            "current": 1795.21,
            "min": 1500.0,
            "max": 2800.0
        },
        {
            "current": 1798.921,
            "min": 1500.0,
            "max": 2800.0
        },
        {
            "current": 2834.74,
            "min": 1500.0,
            "max": 2800.0
        },
        {
            "current": 3742.227,
            "min": 1500.0,
            "max": 2800.0
        },
        {
            "current": 2835.388,
            "min": 1500.0,
            "max": 2800.0
        },
        {
            "current": 2830.9,
            "min": 1500.0,
            "max": 2800.0
        },
        {
            "current": 2834.623,
            "min": 1500.0,
            "max": 2800.0
        },
        {
            "current": 3495.061,
            "min": 1500.0,
            "max": 2800.0
        },
        {
            "current": 2835.538,
            "min": 1500.0,
            "max": 2800.0
        },
        {
            "current": 2833.143,
            "min": 1500.0,
            "max": 2800.0
        },
        {
            "current": 2838.688,
            "min": 1500.0,
            "max": 2800.0
        },
        {
            "current": 2833.676,
            "min": 1500.0,
            "max": 2800.0
        },
        {
            "current": 2838.639,
            "min": 1500.0,
            "max": 2800.0
        },
        {
            "current": 3669.872,
            "min": 1500.0,
            "max": 2800.0
        },
        {
            "current": 2836.142,
            "min": 1500.0,
            "max": 2800.0
        },
        {
            "current": 2835.493,
            "min": 1500.0,
            "max": 2800.0
        },
        {
            "current": 2832.279,
            "min": 1500.0,
            "max": 2800.0
        },
        {
            "current": 3669.628,
            "min": 1500.0,
            "max": 2800.0
        },
        {
            "current": 1532.527,
            "min": 1500.0,
            "max": 2800.0
        },
        {
            "current": 1796.512,
            "min": 1500.0,
            "max": 2800.0
        },
        {
            "current": 1602.589,
            "min": 1500.0,
            "max": 2800.0
        },
        {
            "current": 1496.956,
            "min": 1500.0,
            "max": 2800.0
        },
        {
            "current": 1715.287,
            "min": 1500.0,
            "max": 2800.0
        },
        {
            "current": 1513.531,
            "min": 1500.0,
            "max": 2800.0
        },
        {
            "current": 1748.757,
            "min": 1500.0,
            "max": 2800.0
        },
        {
            "current": 1545.662,
            "min": 1500.0,
            "max": 2800.0
        },
        {
            "current": 2074.668,
            "min": 1500.0,
            "max": 2800.0
        },
        {
            "current": 2138.582,
            "min": 1500.0,
            "max": 2800.0
        },
        {
            "current": 2110.847,
            "min": 1500.0,
            "max": 2800.0
        },
        {
            "current": 1757.879,
            "min": 1500.0,
            "max": 2800.0
        },
        {
            "current": 2812.324,
            "min": 1500.0,
            "max": 2800.0
        },
        {
            "current": 2079.239,
            "min": 1500.0,
            "max": 2800.0
        },
        {
            "current": 2181.14,
            "min": 1500.0,
            "max": 2800.0
        },
        {
            "current": 2165.763,
            "min": 1500.0,
            "max": 2800.0
        },
        {
            "current": 1494.883,
            "min": 1500.0,
            "max": 2800.0
        },
        {
            "current": 1371.667,
            "min": 1500.0,
            "max": 2800.0
        },
        {
            "current": 1496.479,
            "min": 1500.0,
            "max": 2800.0
        },
        {
            "current": 1497.039,
            "min": 1500.0,
            "max": 2800.0
        },
        {
            "current": 1396.972,
            "min": 1500.0,
            "max": 2800.0
        },
        {
            "current": 1353.609,
            "min": 1500.0,
            "max": 2800.0
        },
        {
            "current": 1497.478,
            "min": 1500.0,
            "max": 2800.0
        },
        {
            "current": 1497.921,
            "min": 1500.0,
            "max": 2800.0
        },
        {
            "current": 1497.419,
            "min": 1500.0,
            "max": 2800.0
        },
        {
            "current": 1497.472,
            "min": 1500.0,
            "max": 2800.0
        },
        {
            "current": 1496.406,
            "min": 1500.0,
            "max": 2800.0
        },
        {
            "current": 1496.619,
            "min": 1500.0,
            "max": 2800.0
        },
        {
            "current": 1495.915,
            "min": 1500.0,
            "max": 2800.0
        },
        {
            "current": 1496.647,
            "min": 1500.0,
            "max": 2800.0
        },
        {
            "current": 1496.927,
            "min": 1500.0,
            "max": 2800.0
        },
        {
            "current": 1496.486,
            "min": 1500.0,
            "max": 2800.0
        },
        {
            "current": 2842.703,
            "min": 1500.0,
            "max": 2800.0
        },
        {
            "current": 2842.957,
            "min": 1500.0,
            "max": 2800.0
        },
        {
            "current": 3556.334,
            "min": 1500.0,
            "max": 2800.0
        },
        {
            "current": 1599.386,
            "min": 1500.0,
            "max": 2800.0
        },
        {
            "current": 3553.247,
            "min": 1500.0,
            "max": 2800.0
        },
        {
            "current": 3745.157,
            "min": 1500.0,
            "max": 2800.0
        },
        {
            "current": 2840.501,
            "min": 1500.0,
            "max": 2800.0
        },
        {
            "current": 2849.459,
            "min": 1500.0,
            "max": 2800.0
        },
        {
            "current": 1495.315,
            "min": 1500.0,
            "max": 2800.0
        },
        {
            "current": 1497.381,
            "min": 1500.0,
            "max": 2800.0
        },
        {
            "current": 1496.675,
            "min": 1500.0,
            "max": 2800.0
        },
        {
            "current": 1496.553,
            "min": 1500.0,
            "max": 2800.0
        },
        {
            "current": 3192.342,
            "min": 1500.0,
            "max": 2800.0
        },
        {
            "current": 3170.759,
            "min": 1500.0,
            "max": 2800.0
        },
        {
            "current": 3561.069,
            "min": 1500.0,
            "max": 2800.0
        },
        {
            "current": 3193.573,
            "min": 1500.0,
            "max": 2800.0
        },
        {
            "current": 2971.399,
            "min": 1500.0,
            "max": 2800.0
        },
        {
            "current": 3670.339,
            "min": 1500.0,
            "max": 2800.0
        },
        {
            "current": 2843.295,
            "min": 1500.0,
            "max": 2800.0
        },
        {
            "current": 2840.781,
            "min": 1500.0,
            "max": 2800.0
        },
        {
            "current": 2845.904,
            "min": 1500.0,
            "max": 2800.0
        },
        {
            "current": 3670.092,
            "min": 1500.0,
            "max": 2800.0
        },
        {
            "current": 2845.657,
            "min": 1500.0,
            "max": 2800.0
        },
        {
            "current": 2844.528,
            "min": 1500.0,
            "max": 2800.0
        },
        {
            "current": 2848.78,
            "min": 1500.0,
            "max": 2800.0
        },
        {
            "current": 2952.767,
            "min": 1500.0,
            "max": 2800.0
        },
        {
            "current": 2843.233,
            "min": 1500.0,
            "max": 2800.0
        },
        {
            "current": 3771.852,
            "min": 1500.0,
            "max": 2800.0
        },
        {
            "current": 2842.241,
            "min": 1500.0,
            "max": 2800.0
        },
        {
            "current": 2842.677,
            "min": 1500.0,
            "max": 2800.0
        },
        {
            "current": 2847.147,
            "min": 1500.0,
            "max": 2800.0
        },
        {
            "current": 3559.816,
            "min": 1500.0,
            "max": 2800.0
        },
        {
            "current": 1830.694,
            "min": 1500.0,
            "max": 2800.0
        },
        {
            "current": 2269.28,
            "min": 1500.0,
            "max": 2800.0
        },
        {
            "current": 1768.297,
            "min": 1500.0,
            "max": 2800.0
        },
        {
            "current": 1787.888,
            "min": 1500.0,
            "max": 2800.0
        },
        {
            "current": 2116.084,
            "min": 1500.0,
            "max": 2800.0
        },
        {
            "current": 2007.692,
            "min": 1500.0,
            "max": 2800.0
        },
        {
            "current": 2228.526,
            "min": 1500.0,
            "max": 2800.0
        },
        {
            "current": 2024.189,
            "min": 1500.0,
            "max": 2800.0
        },
        {
            "current": 2109.493,
            "min": 1500.0,
            "max": 2800.0
        },
        {
            "current": 1711.719,
            "min": 1500.0,
            "max": 2800.0
        },
        {
            "current": 1710.776,
            "min": 1500.0,
            "max": 2800.0
        },
        {
            "current": 2120.576,
            "min": 1500.0,
            "max": 2800.0
        },
        {
            "current": 2692.43,
            "min": 1500.0,
            "max": 2800.0
        },
        {
            "current": 2425.622,
            "min": 1500.0,
            "max": 2800.0
        },
        {
            "current": 2099.702,
            "min": 1500.0,
            "max": 2800.0
        },
        {
            "current": 2084.181,
            "min": 1500.0,
            "max": 2800.0
        },
        {
            "current": 1357.341,
            "min": 1500.0,
            "max": 2800.0
        },
        {
            "current": 1482.367,
            "min": 1500.0,
            "max": 2800.0
        },
        {
            "current": 1462.039,
            "min": 1500.0,
            "max": 2800.0
        },
        {
            "current": 1366.402,
            "min": 1500.0,
            "max": 2800.0
        },
        {
            "current": 1377.16,
            "min": 1500.0,
            "max": 2800.0
        },
        {
            "current": 1361.172,
            "min": 1500.0,
            "max": 2800.0
        },
        {
            "current": 1368.299,
            "min": 1500.0,
            "max": 2800.0
        },
        {
            "current": 1372.515,
            "min": 1500.0,
            "max": 2800.0
        },
        {
            "current": 1438.413,
            "min": 1500.0,
            "max": 2800.0
        },
        {
            "current": 1495.733,
            "min": 1500.0,
            "max": 2800.0
        },
        {
            "current": 1496.107,
            "min": 1500.0,
            "max": 2800.0
        },
        {
            "current": 1496.924,
            "min": 1500.0,
            "max": 2800.0
        },
        {
            "current": 1497.212,
            "min": 1500.0,
            "max": 2800.0
        },
        {
            "current": 1497.856,
            "min": 1500.0,
            "max": 2800.0
        },
        {
            "current": 1496.646,
            "min": 1500.0,
            "max": 2800.0
        },
        {
            "current": 1496.488,
            "min": 1500.0,
            "max": 2800.0
        }
    ],
    "disk": {
        "/": {
            "total": 437.88097381591797,
            "used": 116.14691925048828
        }
    },
    "gpu": "NVIDIA A100-SXM4-80GB",
    "gpu_count": 4,
    "gpu_devices": [
        {
            "name": "NVIDIA A100-SXM4-80GB",
            "memory_total": 85899345920
        },
        {
            "name": "NVIDIA A100-SXM4-80GB",
            "memory_total": 85899345920
        },
        {
            "name": "NVIDIA A100-SXM4-80GB",
            "memory_total": 85899345920
        },
        {
            "name": "NVIDIA A100-SXM4-80GB",
            "memory_total": 85899345920
        }
    ],
    "memory": {
        "total": 1007.7270240783691
    }
}