{
    "os": "Linux-5.4.0-162-generic-x86_64-with-glibc2.31",
    "python": "3.10.13",
    "heartbeatAt": "2024-02-19T22:38:13.354889",
    "startedAt": "2024-02-19T22:38:12.981944",
    "docker": null,
    "cuda": null,
    "args": [],
    "state": "running",
    "program": "/sailhome/andukuri/research_projects/assistant-gate/experiments/v3/sft/train/train_sft.py",
    "codePathLocal": "train_sft.py",
    "codePath": "experiments/v3/sft/train/train_sft.py",
    "git": {
        "remote": "git@github.com:scandukuri/assistant-gate.git",
        "commit": "f8363af8df3975a6e7aa8d51faed3673a194e927"
    },
    "email": "andukuri@stanford.edu",
    "root": "/sailhome/andukuri/research_projects/assistant-gate",
    "host": "cocoflops2",
    "username": "andukuri",
    "executable": "/scr/andukuri/miniconda3/envs/assistant-gate/bin/python",
    "cpu_count": 64,
    "cpu_count_logical": 128,
    "cpu_freq": {
        "current": 2277.2770625000003,
        "min": 1500.0,
        "max": 2800.0
    },
    "cpu_freq_per_core": [
        {
            "current": 1499.888,
            "min": 1500.0,
            "max": 2800.0
        },
        {
            "current": 1493.426,
            "min": 1500.0,
            "max": 2800.0
        },
        {
            "current": 1589.308,
            "min": 1500.0,
            "max": 2800.0
        },
        {
            "current": 1498.998,
            "min": 1500.0,
            "max": 2800.0
        },
        {
            "current": 2915.408,
            "min": 1500.0,
            "max": 2800.0
        },
        {
            "current": 2872.163,
            "min": 1500.0,
            "max": 2800.0
        },
        {
            "current": 2907.74,
            "min": 1500.0,
            "max": 2800.0
        },
        {
            "current": 3622.381,
            "min": 1500.0,
            "max": 2800.0
        },
        {
            "current": 3714.639,
            "min": 1500.0,
            "max": 2800.0
        },
        {
            "current": 2506.624,
            "min": 1500.0,
            "max": 2800.0
        },
        {
            "current": 2858.063,
            "min": 1500.0,
            "max": 2800.0
        },
        {
            "current": 2848.543,
            "min": 1500.0,
            "max": 2800.0
        },
        {
            "current": 2853.121,
            "min": 1500.0,
            "max": 2800.0
        },
        {
            "current": 2856.327,
            "min": 1500.0,
            "max": 2800.0
        },
        {
            "current": 3621.588,
            "min": 1500.0,
            "max": 2800.0
        },
        {
            "current": 2853.75,
            "min": 1500.0,
            "max": 2800.0
        },
        {
            "current": 1794.359,
            "min": 1500.0,
            "max": 2800.0
        },
        {
            "current": 1496.651,
            "min": 1500.0,
            "max": 2800.0
        },
        {
            "current": 1495.568,
            "min": 1500.0,
            "max": 2800.0
        },
        {
            "current": 1795.927,
            "min": 1500.0,
            "max": 2800.0
        },
        {
            "current": 1495.893,
            "min": 1500.0,
            "max": 2800.0
        },
        {
            "current": 1498.059,
            "min": 1500.0,
            "max": 2800.0
        },
        {
            "current": 1496.232,
            "min": 1500.0,
            "max": 2800.0
        },
        {
            "current": 1497.848,
            "min": 1500.0,
            "max": 2800.0
        },
        {
            "current": 1496.616,
            "min": 1500.0,
            "max": 2800.0
        },
        {
            "current": 1499.163,
            "min": 1500.0,
            "max": 2800.0
        },
        {
            "current": 1731.529,
            "min": 1500.0,
            "max": 2800.0
        },
        {
            "current": 1656.747,
            "min": 1500.0,
            "max": 2800.0
        },
        {
            "current": 1498.82,
            "min": 1500.0,
            "max": 2800.0
        },
        {
            "current": 1393.895,
            "min": 1500.0,
            "max": 2800.0
        },
        {
            "current": 1496.59,
            "min": 1500.0,
            "max": 2800.0
        },
        {
            "current": 1497.256,
            "min": 1500.0,
            "max": 2800.0
        },
        {
            "current": 2957.417,
            "min": 1500.0,
            "max": 2800.0
        },
        {
            "current": 2955.035,
            "min": 1500.0,
            "max": 2800.0
        },
        {
            "current": 3725.755,
            "min": 1500.0,
            "max": 2800.0
        },
        {
            "current": 2898.565,
            "min": 1500.0,
            "max": 2800.0
        },
        {
            "current": 2893.28,
            "min": 1500.0,
            "max": 2800.0
        },
        {
            "current": 2898.485,
            "min": 1500.0,
            "max": 2800.0
        },
        {
            "current": 3615.349,
            "min": 1500.0,
            "max": 2800.0
        },
        {
            "current": 2892.983,
            "min": 1500.0,
            "max": 2800.0
        },
        {
            "current": 2889.326,
            "min": 1500.0,
            "max": 2800.0
        },
        {
            "current": 2888.532,
            "min": 1500.0,
            "max": 2800.0
        },
        {
            "current": 3619.146,
            "min": 1500.0,
            "max": 2800.0
        },
        {
            "current": 2891.742,
            "min": 1500.0,
            "max": 2800.0
        },
        {
            "current": 2836.483,
            "min": 1500.0,
            "max": 2800.0
        },
        {
            "current": 2841.381,
            "min": 1500.0,
            "max": 2800.0
        },
        {
            "current": 3614.961,
            "min": 1500.0,
            "max": 2800.0
        },
        {
            "current": 2836.002,
            "min": 1500.0,
            "max": 2800.0
        },
        {
            "current": 1497.688,
            "min": 1500.0,
            "max": 2800.0
        },
        {
            "current": 1496.765,
            "min": 1500.0,
            "max": 2800.0
        },
        {
            "current": 1497.467,
            "min": 1500.0,
            "max": 2800.0
        },
        {
            "current": 1497.026,
            "min": 1500.0,
            "max": 2800.0
        },
        {
            "current": 1497.975,
            "min": 1500.0,
            "max": 2800.0
        },
        {
            "current": 1496.959,
            "min": 1500.0,
            "max": 2800.0
        },
        {
            "current": 1496.307,
            "min": 1500.0,
            "max": 2800.0
        },
        {
            "current": 1498.027,
            "min": 1500.0,
            "max": 2800.0
        },
        {
            "current": 1496.751,
            "min": 1500.0,
            "max": 2800.0
        },
        {
            "current": 1497.465,
            "min": 1500.0,
            "max": 2800.0
        },
        {
            "current": 1497.024,
            "min": 1500.0,
            "max": 2800.0
        },
        {
            "current": 1497.493,
            "min": 1500.0,
            "max": 2800.0
        },
        {
            "current": 1499.076,
            "min": 1500.0,
            "max": 2800.0
        },
        {
            "current": 1496.883,
            "min": 1500.0,
            "max": 2800.0
        },
        {
            "current": 1497.582,
            "min": 1500.0,
            "max": 2800.0
        },
        {
            "current": 1496.975,
            "min": 1500.0,
            "max": 2800.0
        },
        {
            "current": 1499.949,
            "min": 1500.0,
            "max": 2800.0
        },
        {
            "current": 1495.377,
            "min": 1500.0,
            "max": 2800.0
        },
        {
            "current": 1496.827,
            "min": 1500.0,
            "max": 2800.0
        },
        {
            "current": 1497.434,
            "min": 1500.0,
            "max": 2800.0
        },
        {
            "current": 2968.961,
            "min": 1500.0,
            "max": 2800.0
        },
        {
            "current": 2870.463,
            "min": 1500.0,
            "max": 2800.0
        },
        {
            "current": 2858.511,
            "min": 1500.0,
            "max": 2800.0
        },
        {
            "current": 3681.114,
            "min": 1500.0,
            "max": 2800.0
        },
        {
            "current": 3622.446,
            "min": 1500.0,
            "max": 2800.0
        },
        {
            "current": 2957.746,
            "min": 1500.0,
            "max": 2800.0
        },
        {
            "current": 2841.278,
            "min": 1500.0,
            "max": 2800.0
        },
        {
            "current": 2837.999,
            "min": 1500.0,
            "max": 2800.0
        },
        {
            "current": 2842.955,
            "min": 1500.0,
            "max": 2800.0
        },
        {
            "current": 2859.398,
            "min": 1500.0,
            "max": 2800.0
        },
        {
            "current": 3555.129,
            "min": 1500.0,
            "max": 2800.0
        },
        {
            "current": 2847.624,
            "min": 1500.0,
            "max": 2800.0
        },
        {
            "current": 2528.773,
            "min": 1500.0,
            "max": 2800.0
        },
        {
            "current": 2070.556,
            "min": 1500.0,
            "max": 2800.0
        },
        {
            "current": 2068.176,
            "min": 1500.0,
            "max": 2800.0
        },
        {
            "current": 2502.641,
            "min": 1500.0,
            "max": 2800.0
        },
        {
            "current": 1495.63,
            "min": 1500.0,
            "max": 2800.0
        },
        {
            "current": 1496.859,
            "min": 1500.0,
            "max": 2800.0
        },
        {
            "current": 1496.282,
            "min": 1500.0,
            "max": 2800.0
        },
        {
            "current": 1497.952,
            "min": 1500.0,
            "max": 2800.0
        },
        {
            "current": 1499.325,
            "min": 1500.0,
            "max": 2800.0
        },
        {
            "current": 1597.013,
            "min": 1500.0,
            "max": 2800.0
        },
        {
            "current": 1738.329,
            "min": 1500.0,
            "max": 2800.0
        },
        {
            "current": 1552.842,
            "min": 1500.0,
            "max": 2800.0
        },
        {
            "current": 1497.687,
            "min": 1500.0,
            "max": 2800.0
        },
        {
            "current": 1497.59,
            "min": 1500.0,
            "max": 2800.0
        },
        {
            "current": 1497.177,
            "min": 1500.0,
            "max": 2800.0
        },
        {
            "current": 1496.213,
            "min": 1500.0,
            "max": 2800.0
        },
        {
            "current": 2840.813,
            "min": 1500.0,
            "max": 2800.0
        },
        {
            "current": 2832.675,
            "min": 1500.0,
            "max": 2800.0
        },
        {
            "current": 3614.836,
            "min": 1500.0,
            "max": 2800.0
        },
        {
            "current": 2837.535,
            "min": 1500.0,
            "max": 2800.0
        },
        {
            "current": 3158.465,
            "min": 1500.0,
            "max": 2800.0
        },
        {
            "current": 3215.153,
            "min": 1500.0,
            "max": 2800.0
        },
        {
            "current": 3550.27,
            "min": 1500.0,
            "max": 2800.0
        },
        {
            "current": 2835.133,
            "min": 1500.0,
            "max": 2800.0
        },
        {
            "current": 2836.476,
            "min": 1500.0,
            "max": 2800.0
        },
        {
            "current": 2839.125,
            "min": 1500.0,
            "max": 2800.0
        },
        {
            "current": 3614.302,
            "min": 1500.0,
            "max": 2800.0
        },
        {
            "current": 2835.048,
            "min": 1500.0,
            "max": 2800.0
        },
        {
            "current": 2838.022,
            "min": 1500.0,
            "max": 2800.0
        },
        {
            "current": 2834.292,
            "min": 1500.0,
            "max": 2800.0
        },
        {
            "current": 3548.598,
            "min": 1500.0,
            "max": 2800.0
        },
        {
            "current": 2888.094,
            "min": 1500.0,
            "max": 2800.0
        },
        {
            "current": 1497.327,
            "min": 1500.0,
            "max": 2800.0
        },
        {
            "current": 1496.802,
            "min": 1500.0,
            "max": 2800.0
        },
        {
            "current": 1497.49,
            "min": 1500.0,
            "max": 2800.0
        },
        {
            "current": 1497.887,
            "min": 1500.0,
            "max": 2800.0
        },
        {
            "current": 1497.211,
            "min": 1500.0,
            "max": 2800.0
        },
        {
            "current": 1497.105,
            "min": 1500.0,
            "max": 2800.0
        },
        {
            "current": 1497.695,
            "min": 1500.0,
            "max": 2800.0
        },
        {
            "current": 1496.266,
            "min": 1500.0,
            "max": 2800.0
        },
        {
            "current": 1497.142,
            "min": 1500.0,
            "max": 2800.0
        },
        {
            "current": 1496.822,
            "min": 1500.0,
            "max": 2800.0
        },
        {
            "current": 1496.799,
            "min": 1500.0,
            "max": 2800.0
        },
        {
            "current": 1496.548,
            "min": 1500.0,
            "max": 2800.0
        },
        {
            "current": 1498.11,
            "min": 1500.0,
            "max": 2800.0
        },
        {
            "current": 1496.383,
            "min": 1500.0,
            "max": 2800.0
        },
        {
            "current": 1497.145,
            "min": 1500.0,
            "max": 2800.0
        },
        {
            "current": 1497.638,
            "min": 1500.0,
            "max": 2800.0
        }
    ],
    "disk": {
        "/": {
            "total": 437.88097381591797,
            "used": 130.19091033935547
        }
    },
    "gpu": "NVIDIA A100-SXM4-80GB",
    "gpu_count": 1,
    "gpu_devices": [
        {
            "name": "NVIDIA A100-SXM4-80GB",
            "memory_total": 85899345920
        }
    ],
    "memory": {
        "total": 1007.7270240783691
    }
}
